README.md
setup.cfg
setup.py
ppt/__init__.py
ppt/cuda.py
ppt/dashboard.py
ppt/decorators.py
ppt/plotter.py
ppt/profiler.py
ppt.egg-info/PKG-INFO
ppt.egg-info/SOURCES.txt
ppt.egg-info/dependency_links.txt
ppt.egg-info/requires.txt
ppt.egg-info/top_level.txt