Metadata-Version: 2.1
Name: ppt
Version: 0.0.7.1
Summary: The Python Performance Tuner
Home-page: http://www.seba1511.com
Author: Seb Arnold
Author-email: smr.arnold@gmail.com
License: License :: OSI Approved :: Apache Software License
Download-URL: https://github.com/seba-1511/ppt/archive/0.0.7.1.zip
Platform: UNKNOWN
